paired_end_debarcoder/__init__.py
paired_end_debarcoder/barcodes.py
paired_end_debarcoder/demultiplexfasta.py
paired_end_debarcoder/demultiplexfasta_parallel.py
paired_end_debarcoder/demultiplexfastq.py
paired_end_debarcoder/fastq_concat.py
paired_end_debarcoder-0.1.0.dist-info/DESCRIPTION.rst
paired_end_debarcoder-0.1.0.dist-info/METADATA
paired_end_debarcoder-0.1.0.dist-info/RECORD
paired_end_debarcoder-0.1.0.dist-info/WHEEL
paired_end_debarcoder-0.1.0.dist-info/entry_points.txt
paired_end_debarcoder-0.1.0.dist-info/metadata.json
paired_end_debarcoder-0.1.0.dist-info/top_level.txt
